LazyProphet/FourierBasisFunction.py
LazyProphet/LazyProphet.py
LazyProphet/LinearBasisFunction.py
LazyProphet/Optimizer.py
LazyProphet/__init__.py
LazyProphet-0.3.9.dist-info/LICENSE
LazyProphet-0.3.9.dist-info/METADATA
LazyProphet-0.3.9.dist-info/WHEEL
LazyProphet-0.3.9.dist-info/top_level.txt
LazyProphet-0.3.9.dist-info/RECORD
