Metadata-Version: 2.1
Name: LazyProphet
Version: 0.3.9
Summary: Time series forecasting with LightGBM
Home-page: https://github.com/tblume1992/LazyProphet
Author: Tyler Blume
Author-email: tblume@mail.USF.edu
Keywords: forecasting,time series,lightgbm
Classifier: Programming Language :: Python :: 3
Classifier: License :: OSI Approved :: MIT License
Classifier: Operating System :: OS Independent
License-File: LICENSE
Requires-Dist: numpy
Requires-Dist: pandas
Requires-Dist: statsmodels
Requires-Dist: scikit-learn
Requires-Dist: optuna
Requires-Dist: scipy
Requires-Dist: matplotlib
Requires-Dist: lightgbm
